Metadata-Version: 2.1
Name: lirc2hass
Version: 0.1.0
Summary: Bridge LIRC input events to Home Assistant via REST API.
Home-page: https://github.com/crowbarz/lirc2hass
Author: Crowbar Z
Author-email: crowbarz@outlook.com
License: MIT
Keywords: lirc hass mce logitech harmony inputlirc home assistant rest
Platform: UNKNOWN
Classifier: Development Status :: 5 - Production/Stable
Classifier: Intended Audience :: Developers
Classifier: Operating System :: POSIX :: Linux
Classifier: License :: OSI Approved :: MIT License
Classifier: Programming Language :: Python
Classifier: Programming Language :: Python :: 3.6
Classifier: Topic :: Multimedia
Requires-Python: >=3.6
